generated RTL/specified/priority_encoder_8bit.syn.v
module priority_encoder_8bit ( data_in, binary_out, active );
  input [7:0] data_in;
  output reg [2:0] binary_out;
  output reg active;

  always @(*) begin
    active = |data_in;
    binary_out = 3'b000;

    casex (data_in)
      8'b1xxxxxxx: binary_out = 3'b111;
      8'b01xxxxxx: binary_out = 3'b110;
      8'b001xxxxx: binary_out = 3'b101;
      8'b0001xxxx: binary_out = 3'b100;
      8'b00001xxx: binary_out = 3'b011;
      8'b000001xx: binary_out = 3'b010;
      8'b0000001x: binary_out = 3'b001;
      8'b00000001: binary_out = 3'b000;
      default:    binary_out = 3'b000;
    endcase
  end

endmodule

testbench/specified/tb_priority_encoder_8bit.syn.v
module tb_priority_encoder_8bit;

  reg  [7:0] data_in;
  wire [2:0] binary_out;
  wire       active;

  reg  [2:0] expected_binary_out;
  reg        expected_active;
  integer    i;

  priority_encoder_8bit dut (
    .data_in(data_in),
    .binary_out(binary_out),
    .active(active)
  );

  task check_outputs;
    begin
      expected_active = |data_in;
      expected_binary_out = 3'b000;

      if (data_in[7])
        expected_binary_out = 3'b111;
      else if (data_in[6])
        expected_binary_out = 3'b110;
      else if (data_in[5])
        expected_binary_out = 3'b101;
      else if (data_in[4])
        expected_binary_out = 3'b100;
      else if (data_in[3])
        expected_binary_out = 3'b011;
      else if (data_in[2])
        expected_binary_out = 3'b010;
      else if (data_in[1])
        expected_binary_out = 3'b001;
      else if (data_in[0])
        expected_binary_out = 3'b000;
      else
        expected_binary_out = 3'b000;

      if ((active !== expected_active) || (binary_out !== expected_binary_out)) begin
        $display("ERROR: data_in=%b expected active=%b binary_out=%b, got active=%b binary_out=%b",
                 data_in, expected_active, expected_binary_out, active, binary_out);
        $fatal(1);
      end
    end
  endtask

  initial begin
    $dumpfile("dump.vcd");
    $dumpvars(0, tb_priority_encoder_8bit);

    $display("Starting priority_encoder_8bit testbench");
    $monitor("time=%0t data_in=%b active=%b binary_out=%b", $time, data_in, active, binary_out);

    for (i = 0; i < 256; i = i + 1) begin
      data_in = i[7:0];
      #1;
      check_outputs;
    end

    $display("All tests passed.");
    $finish;
  end

endmodule

dump.vcd
$date
	Wed Apr 08 01:45:47 2026
$end
$version
	Icarus Verilog
$end
$timescale
	1s
$end
$scope module tb_priority_encoder_8bit $end
$var wire 3 ! binary_out [2:0] $end
$var wire 1 " active $end
$var reg 8 # data_in [7:0] $end
$var reg 1 $ expected_active $end
$var reg 3 % expected_binary_out [2:0] $end
$var integer 32 & i [31:0] $end
$scope module dut $end
$var wire 8 ' data_in [7:0] $end
$var reg 1 " active $end
$var reg 3 ( binary_out [2:0] $end
$upscope $end
$scope task check_outputs $end
$upscope $end
$upscope $end
$enddefinitions $end
#0
$dumpvars
b0 (
b0 '
b0 &
bx %
x$
b0 #
0"
b0 !
$end
#1
1"
b1 #
b1 '
b1 &
b0 %
0$
#2
b1 !
b1 (
b10 #
b10 '
b10 &
1$
#3
b1 !
b1 (
b11 #
b11 '
b11 &
b1 %
#4
b10 !
b10 (
b100 #
b100 '
b100 &
b1 %
#5
b10 !
b10 (
b101 #
b101 '
b101 &
b10 %
#6
b10 !
b10 (
b110 #
b110 '
b110 &
b10 %
#7
b10 !
b10 (
b111 #
b111 '
b111 &
b10 %
#8
b11 !
b11 (
b1000 #
b1000 '
b1000 &
b10 %
#9
b11 !
b11 (
b1001 #
b1001 '
b1001 &
b11 %
#10
b11 !
b11 (
b1010 #
b1010 '
b1010 &
b11 %
#11
b11 !
b11 (
b1011 #
b1011 '
b1011 &
b11 %
#12
b11 !
b11 (
b1100 #
b1100 '
b1100 &
b11 %
#13
b11 !
b11 (
b1101 #
b1101 '
b1101 &
b11 %
#14
b11 !
b11 (
b1110 #
b1110 '
b1110 &
b11 %
#15
b11 !
b11 (
b1111 #
b1111 '
b1111 &
b11 %
#16
b100 !
b100 (
b10000 #
b10000 '
b10000 &
b11 %
#17
b100 !
b100 (
b10001 #
b10001 '
b10001 &
b100 %
#18
b100 !
b100 (
b10010 #
b10010 '
b10010 &
b100 %
#19
b100 !
b100 (
b10011 #
b10011 '
b10011 &
b100 %
#20
b100 !
b100 (
b10100 #
b10100 '
b10100 &
b100 %
#21
b100 !
b100 (
b10101 #
b10101 '
b10101 &
b100 %
#22
b100 !
b100 (
b10110 #
b10110 '
b10110 &
b100 %
#23
b100 !
b100 (
b10111 #
b10111 '
b10111 &
b100 %
#24
b100 !
b100 (
b11000 #
b11000 '
b11000 &
b100 %
#25
b100 !
b100 (
b11001 #
b11001 '
b11001 &
b100 %
#26
b100 !
b100 (
b11010 #
b11010 '
b11010 &
b100 %
#27
b100 !
b100 (
b11011 #
b11011 '
b11011 &
b100 %
#28
b100 !
b100 (
b11100 #
b11100 '
b11100 &
b100 %
#29
b100 !
b100 (
b11101 #
b11101 '
b11101 &
b100 %
#30
b100 !
b100 (
b11110 #
b11110 '
b11110 &
b100 %
#31
b100 !
b100 (
b11111 #
b11111 '
b11111 &
b100 %
#32
b101 !
b101 (
b100000 #
b100000 '
b100000 &
b100 %
#33
b101 !
b101 (
b100001 #
b100001 '
b100001 &
b101 %
#34
b101 !
b101 (
b100010 #
b100010 '
b100010 &
b101 %
#35
b101 !
b101 (
b100011 #
b100011 '
b100011 &
b101 %
#36
b101 !
b101 (
b100100 #
b100100 '
b100100 &
b101 %
#37
b101 !
b101 (
b100101 #
b100101 '
b100101 &
b101 %
#38
b101 !
b101 (
b100110 #
b100110 '
b100110 &
b101 %
#39
b101 !
b101 (
b100111 #
b100111 '
b100111 &
b101 %
#40
b101 !
b101 (
b101000 #
b101000 '
b101000 &
b101 %
#41
b101 !
b101 (
b101001 #
b101001 '
b101001 &
b101 %
#42
b101 !
b101 (
b101010 #
b101010 '
b101010 &
b101 %
#43
b101 !
b101 (
b101011 #
b101011 '
b101011 &
b101 %
#44
b101 !
b101 (
b101100 #
b101100 '
b101100 &
b101 %
#45
b101 !
b101 (
b101101 #
b101101 '
b101101 &
b101 %
#46
b101 !
b101 (
b101110 #
b101110 '
b101110 &
b101 %
#47
b101 !
b101 (
b101111 #
b101111 '
b101111 &
b101 %
#48
b101 !
b101 (
b110000 #
b110000 '
b110000 &
b101 %
#49
b101 !
b101 (
b110001 #
b110001 '
b110001 &
b101 %
#50
b101 !
b101 (
b110010 #
b110010 '
b110010 &
b101 %
#51
b101 !
b101 (
b110011 #
b110011 '
b110011 &
b101 %
#52
b101 !
b101 (
b110100 #
b110100 '
b110100 &
b101 %
#53
b101 !
b101 (
b110101 #
b110101 '
b110101 &
b101 %
#54
b101 !
b101 (
b110110 #
b110110 '
b110110 &
b101 %
#55
b101 !
b101 (
b110111 #
b110111 '
b110111 &
b101 %
#56
b101 !
b101 (
b111000 #
b111000 '
b111000 &
b101 %
#57
b101 !
b101 (
b111001 #
b111001 '
b111001 &
b101 %
#58
b101 !
b101 (
b111010 #
b111010 '
b111010 &
b101 %
#59
b101 !
b101 (
b111011 #
b111011 '
b111011 &
b101 %
#60
b101 !
b101 (
b111100 #
b111100 '
b111100 &
b101 %
#61
b101 !
b101 (
b111101 #
b111101 '
b111101 &
b101 %
#62
b101 !
b101 (
b111110 #
b111110 '
b111110 &
b101 %
#63
b101 !
b101 (
b111111 #
b111111 '
b111111 &
b101 %
#64
b110 !
b110 (
b1000000 #
b1000000 '
b1000000 &
b101 %
#65
b110 !
b110 (
b1000001 #
b1000001 '
b1000001 &
b110 %
#66
b110 !
b110 (
b1000010 #
b1000010 '
b1000010 &
b110 %
#67
b110 !
b110 (
b1000011 #
b1000011 '
b1000011 &
b110 %
#68
b110 !
b110 (
b1000100 #
b1000100 '
b1000100 &
b110 %
#69
b110 !
b110 (
b1000101 #
b1000101 '
b1000101 &
b110 %
#70
b110 !
b110 (
b1000110 #
b1000110 '
b1000110 &
b110 %
#71
b110 !
b110 (
b1000111 #
b1000111 '
b1000111 &
b110 %
#72
b110 !
b110 (
b1001000 #
b1001000 '
b1001000 &
b110 %
#73
b110 !
b110 (
b1001001 #
b1001001 '
b1001001 &
b110 %
#74
b110 !
b110 (
b1001010 #
b1001010 '
b1001010 &
b110 %
#75
b110 !
b110 (
b1001011 #
b1001011 '
b1001011 &
b110 %
#76
b110 !
b110 (
b1001100 #
b1001100 '
b1001100 &
b110 %
#77
b110 !
b110 (
b1001101 #
b1001101 '
b1001101 &
b110 %
#78
b110 !
b110 (
b1001110 #
b1001110 '
b1001110 &
b110 %
#79
b110 !
b110 (
b1001111 #
b1001111 '
b1001111 &
b110 %
#80
b110 !
b110 (
b1010000 #
b1010000 '
b1010000 &
b110 %
#81
b110 !
b110 (
b1010001 #
b1010001 '
b1010001 &
b110 %
#82
b110 !
b110 (
b1010010 #
b1010010 '
b1010010 &
b110 %
#83
b110 !
b110 (
b1010011 #
b1010011 '
b1010011 &
b110 %
#84
b110 !
b110 (
b1010100 #
b1010100 '
b1010100 &
b110 %
#85
b110 !
b110 (
b1010101 #
b1010101 '
b1010101 &
b110 %
#86
b110 !
b110 (
b1010110 #
b1010110 '
b1010110 &
b110 %
#87
b110 !
b110 (
b1010111 #
b1010111 '
b1010111 &
b110 %
#88
b110 !
b110 (
b1011000 #
b1011000 '
b1011000 &
b110 %
#89
b110 !
b110 (
b1011001 #
b1011001 '
b1011001 &
b110 %
#90
b110 !
b110 (
b1011010 #
b1011010 '
b1011010 &
b110 %
#91
b110 !
b110 (
b1011011 #
b1011011 '
b1011011 &
b110 %
#92
b110 !
b110 (
b1011100 #
b1011100 '
b1011100 &
b110 %
#93
b110 !
b110 (
b1011101 #
b1011101 '
b1011101 &
b110 %
#94
b110 !
b110 (
b1011110 #
b1011110 '
b1011110 &
b110 %
#95
b110 !
b110 (
b1011111 #
b1011111 '
b1011111 &
b110 %
#96
b110 !
b110 (
b1100000 #
b1100000 '
b1100000 &
b110 %
#97
b110 !
b110 (
b1100001 #
b1100001 '
b1100001 &
b110 %
#98
b110 !
b110 (
b1100010 #
b1100010 '
b1100010 &
b110 %
#99
b110 !
b110 (
b1100011 #
b1100011 '
b1100011 &
b110 %
#100
b110 !
b110 (
b1100100 #
b1100100 '
b1100100 &
b110 %
#101
b110 !
b110 (
b1100101 #
b1100101 '
b1100101 &
b110 %
#102
b110 !
b110 (
b1100110 #
b1100110 '
b1100110 &
b110 %
#103
b110 !
b110 (
b1100111 #
b1100111 '
b1100111 &
b110 %
#104
b110 !
b110 (
b1101000 #
b1101000 '
b1101000 &
b110 %
#105
b110 !
b110 (
b1101001 #
b1101001 '
b1101001 &
b110 %
#106
b110 !
b110 (
b1101010 #
b1101010 '
b1101010 &
b110 %
#107
b110 !
b110 (
b1101011 #
b1101011 '
b1101011 &
b110 %
#108
b110 !
b110 (
b1101100 #
b1101100 '
b1101100 &
b110 %
#109
b110 !
b110 (
b1101101 #
b1101101 '
b1101101 &
b110 %
#110
b110 !
b110 (
b1101110 #
b1101110 '
b1101110 &
b110 %
#111
b110 !
b110 (
b1101111 #
b1101111 '
b1101111 &
b110 %
#112
b110 !
b110 (
b1110000 #
b1110000 '
b1110000 &
b110 %
#113
b110 !
b110 (
b1110001 #
b1110001 '
b1110001 &
b110 %
#114
b110 !
b110 (
b1110010 #
b1110010 '
b1110010 &
b110 %
#115
b110 !
b110 (
b1110011 #
b1110011 '
b1110011 &
b110 %
#116
b110 !
b110 (
b1110100 #
b1110100 '
b1110100 &
b110 %
#117
b110 !
b110 (
b1110101 #
b1110101 '
b1110101 &
b110 %
#118
b110 !
b110 (
b1110110 #
b1110110 '
b1110110 &
b110 %
#119
b110 !
b110 (
b1110111 #
b1110111 '
b1110111 &
b110 %
#120
b110 !
b110 (
b1111000 #
b1111000 '
b1111000 &
b110 %
#121
b110 !
b110 (
b1111001 #
b1111001 '
b1111001 &
b110 %
#122
b110 !
b110 (
b1111010 #
b1111010 '
b1111010 &
b110 %
#123
b110 !
b110 (
b1111011 #
b1111011 '
b1111011 &
b110 %
#124
b110 !
b110 (
b1111100 #
b1111100 '
b1111100 &
b110 %
#125
b110 !
b110 (
b1111101 #
b1111101 '
b1111101 &
b110 %
#126
b110 !
b110 (
b1111110 #
b1111110 '
b1111110 &
b110 %
#127
b110 !
b110 (
b1111111 #
b1111111 '
b1111111 &
b110 %
#128
b111 !
b111 (
b10000000 #
b10000000 '
b10000000 &
b110 %
#129
b111 !
b111 (
b10000001 #
b10000001 '
b10000001 &
b111 %
#130
b111 !
b111 (
b10000010 #
b10000010 '
b10000010 &
b111 %
#131
b111 !
b111 (
b10000011 #
b10000011 '
b10000011 &
b111 %
#132
b111 !
b111 (
b10000100 #
b10000100 '
b10000100 &
b111 %
#133
b111 !
b111 (
b10000101 #
b10000101 '
b10000101 &
b111 %
#134
b111 !
b111 (
b10000110 #
b10000110 '
b10000110 &
b111 %
#135
b111 !
b111 (
b10000111 #
b10000111 '
b10000111 &
b111 %
#136
b111 !
b111 (
b10001000 #
b10001000 '
b10001000 &
b111 %
#137
b111 !
b111 (
b10001001 #
b10001001 '
b10001001 &
b111 %
#138
b111 !
b111 (
b10001010 #
b10001010 '
b10001010 &
b111 %
#139
b111 !
b111 (
b10001011 #
b10001011 '
b10001011 &
b111 %
#140
b111 !
b111 (
b10001100 #
b10001100 '
b10001100 &
b111 %
#141
b111 !
b111 (
b10001101 #
b10001101 '
b10001101 &
b111 %
#142
b111 !
b111 (
b10001110 #
b10001110 '
b10001110 &
b111 %
#143
b111 !
b111 (
b10001111 #
b10001111 '
b10001111 &
b111 %
#144
b111 !
b111 (
b10010000 #
b10010000 '
b10010000 &
b111 %
#145
b111 !
b111 (
b10010001 #
b10010001 '
b10010001 &
b111 %
#146
b111 !
b111 (
b10010010 #
b10010010 '
b10010010 &
b111 %
#147
b111 !
b111 (
b10010011 #
b10010011 '
b10010011 &
b111 %
#148
b111 !
b111 (
b10010100 #
b10010100 '
b10010100 &
b111 %
#149
b111 !
b111 (
b10010101 #
b10010101 '
b10010101 &
b111 %
#150
b111 !
b111 (
b10010110 #
b10010110 '
b10010110 &
b111 %
#151
b111 !
b111 (
b10010111 #
b10010111 '
b10010111 &
b111 %
#152
b111 !
b111 (
b10011000 #
b10011000 '
b10011000 &
b111 %
#153
b111 !
b111 (
b10011001 #
b10011001 '
b10011001 &
b111 %
#154
b111 !
b111 (
b10011010 #
b10011010 '
b10011010 &
b111 %
#155
b111 !
b111 (
b10011011 #
b10011011 '
b10011011 &
b111 %
#156
b111 !
b111 (
b10011100 #
b10011100 '
b10011100 &
b111 %
#157
b111 !
b111 (
b10011101 #
b10011101 '
b10011101 &
b111 %
#158
b111 !
b111 (
b10011110 #
b10011110 '
b10011110 &
b111 %
#159
b111 !
b111 (
b10011111 #
b10011111 '
b10011111 &
b111 %
#160
b111 !
b111 (
b10100000 #
b10100000 '
b10100000 &
b111 %
#161
b111 !
b111 (
b10100001 #
b10100001 '
b10100001 &
b111 %
#162
b111 !
b111 (
b10100010 #
b10100010 '
b10100010 &
b111 %
#163
b111 !
b111 (
b10100011 #
b10100011 '
b10100011 &
b111 %
#164
b111 !
b111 (
b10100100 #
b10100100 '
b10100100 &
b111 %
#165
b111 !
b111 (
b10100101 #
b10100101 '
b10100101 &
b111 %
#166
b111 !
b111 (
b10100110 #
b10100110 '
b10100110 &
b111 %
#167
b111 !
b111 (
b10100111 #
b10100111 '
b10100111 &
b111 %
#168
b111 !
b111 (
b10101000 #
b10101000 '
b10101000 &
b111 %
#169
b111 !
b111 (
b10101001 #
b10101001 '
b10101001 &
b111 %
#170
b111 !
b111 (
b10101010 #
b10101010 '
b10101010 &
b111 %
#171
b111 !
b111 (
b10101011 #
b10101011 '
b10101011 &
b111 %
#172
b111 !
b111 (
b10101100 #
b10101100 '
b10101100 &
b111 %
#173
b111 !
b111 (
b10101101 #
b10101101 '
b10101101 &
b111 %
#174
b111 !
b111 (
b10101110 #
b10101110 '
b10101110 &
b111 %
#175
b111 !
b111 (
b10101111 #
b10101111 '
b10101111 &
b111 %
#176
b111 !
b111 (
b10110000 #
b10110000 '
b10110000 &
b111 %
#177
b111 !
b111 (
b10110001 #
b10110001 '
b10110001 &
b111 %
#178
b111 !
b111 (
b10110010 #
b10110010 '
b10110010 &
b111 %
#179
b111 !
b111 (
b10110011 #
b10110011 '
b10110011 &
b111 %
#180
b111 !
b111 (
b10110100 #
b10110100 '
b10110100 &
b111 %
#181
b111 !
b111 (
b10110101 #
b10110101 '
b10110101 &
b111 %
#182
b111 !
b111 (
b10110110 #
b10110110 '
b10110110 &
b111 %
#183
b111 !
b111 (
b10110111 #
b10110111 '
b10110111 &
b111 %
#184
b111 !
b111 (
b10111000 #
b10111000 '
b10111000 &
b111 %
#185
b111 !
b111 (
b10111001 #
b10111001 '
b10111001 &
b111 %
#186
b111 !
b111 (
b10111010 #
b10111010 '
b10111010 &
b111 %
#187
b111 !
b111 (
b10111011 #
b10111011 '
b10111011 &
b111 %
#188
b111 !
b111 (
b10111100 #
b10111100 '
b10111100 &
b111 %
#189
b111 !
b111 (
b10111101 #
b10111101 '
b10111101 &
b111 %
#190
b111 !
b111 (
b10111110 #
b10111110 '
b10111110 &
b111 %
#191
b111 !
b111 (
b10111111 #
b10111111 '
b10111111 &
b111 %
#192
b111 !
b111 (
b11000000 #
b11000000 '
b11000000 &
b111 %
#193
b111 !
b111 (
b11000001 #
b11000001 '
b11000001 &
b111 %
#194
b111 !
b111 (
b11000010 #
b11000010 '
b11000010 &
b111 %
#195
b111 !
b111 (
b11000011 #
b11000011 '
b11000011 &
b111 %
#196
b111 !
b111 (
b11000100 #
b11000100 '
b11000100 &
b111 %
#197
b111 !
b111 (
b11000101 #
b11000101 '
b11000101 &
b111 %
#198
b111 !
b111 (
b11000110 #
b11000110 '
b11000110 &
b111 %
#199
b111 !
b111 (
b11000111 #
b11000111 '
b11000111 &
b111 %
#200
b111 !
b111 (
b11001000 #
b11001000 '
b11001000 &
b111 %
#201
b111 !
b111 (
b11001001 #
b11001001 '
b11001001 &
b111 %
#202
b111 !
b111 (
b11001010 #
b11001010 '
b11001010 &
b111 %
#203
b111 !
b111 (
b11001011 #
b11001011 '
b11001011 &
b111 %
#204
b111 !
b111 (
b11001100 #
b11001100 '
b11001100 &
b111 %
#205
b111 !
b111 (
b11001101 #
b11001101 '
b11001101 &
b111 %
#206
b111 !
b111 (
b11001110 #
b11001110 '
b11001110 &
b111 %
#207
b111 !
b111 (
b11001111 #
b11001111 '
b11001111 &
b111 %
#208
b111 !
b111 (
b11010000 #
b11010000 '
b11010000 &
b111 %
#209
b111 !
b111 (
b11010001 #
b11010001 '
b11010001 &
b111 %
#210
b111 !
b111 (
b11010010 #
b11010010 '
b11010010 &
b111 %
#211
b111 !
b111 (
b11010011 #
b11010011 '
b11010011 &
b111 %
#212
b111 !
b111 (
b11010100 #
b11010100 '
b11010100 &
b111 %
#213
b111 !
b111 (
b11010101 #
b11010101 '
b11010101 &
b111 %
#214
b111 !
b111 (
b11010110 #
b11010110 '
b11010110 &
b111 %
#215
b111 !
b111 (
b11010111 #
b11010111 '
b11010111 &
b111 %
#216
b111 !
b111 (
b11011000 #
b11011000 '
b11011000 &
b111 %
#217
b111 !
b111 (
b11011001 #
b11011001 '
b11011001 &
b111 %
#218
b111 !
b111 (
b11011010 #
b11011010 '
b11011010 &
b111 %
#219
b111 !
b111 (
b11011011 #
b11011011 '
b11011011 &
b111 %
#220
b111 !
b111 (
b11011100 #
b11011100 '
b11011100 &
b111 %
#221
b111 !
b111 (
b11011101 #
b11011101 '
b11011101 &
b111 %
#222
b111 !
b111 (
b11011110 #
b11011110 '
b11011110 &
b111 %
#223
b111 !
b111 (
b11011111 #
b11011111 '
b11011111 &
b111 %
#224
b111 !
b111 (
b11100000 #
b11100000 '
b11100000 &
b111 %
#225
b111 !
b111 (
b11100001 #
b11100001 '
b11100001 &
b111 %
#226
b111 !
b111 (
b11100010 #
b11100010 '
b11100010 &
b111 %
#227
b111 !
b111 (
b11100011 #
b11100011 '
b11100011 &
b111 %
#228
b111 !
b111 (
b11100100 #
b11100100 '
b11100100 &
b111 %
#229
b111 !
b111 (
b11100101 #
b11100101 '
b11100101 &
b111 %
#230
b111 !
b111 (
b11100110 #
b11100110 '
b11100110 &
b111 %
#231
b111 !
b111 (
b11100111 #
b11100111 '
b11100111 &
b111 %
#232
b111 !
b111 (
b11101000 #
b11101000 '
b11101000 &
b111 %
#233
b111 !
b111 (
b11101001 #
b11101001 '
b11101001 &
b111 %
#234
b111 !
b111 (
b11101010 #
b11101010 '
b11101010 &
b111 %
#235
b111 !
b111 (
b11101011 #
b11101011 '
b11101011 &
b111 %
#236
b111 !
b111 (
b11101100 #
b11101100 '
b11101100 &
b111 %
#237
b111 !
b111 (
b11101101 #
b11101101 '
b11101101 &
b111 %
#238
b111 !
b111 (
b11101110 #
b11101110 '
b11101110 &
b111 %
#239
b111 !
b111 (
b11101111 #
b11101111 '
b11101111 &
b111 %
#240
b111 !
b111 (
b11110000 #
b11110000 '
b11110000 &
b111 %
#241
b111 !
b111 (
b11110001 #
b11110001 '
b11110001 &
b111 %
#242
b111 !
b111 (
b11110010 #
b11110010 '
b11110010 &
b111 %
#243
b111 !
b111 (
b11110011 #
b11110011 '
b11110011 &
b111 %
#244
b111 !
b111 (
b11110100 #
b11110100 '
b11110100 &
b111 %
#245
b111 !
b111 (
b11110101 #
b11110101 '
b11110101 &
b111 %
#246
b111 !
b111 (
b11110110 #
b11110110 '
b11110110 &
b111 %
#247
b111 !
b111 (
b11110111 #
b11110111 '
b11110111 &
b111 %
#248
b111 !
b111 (
b11111000 #
b11111000 '
b11111000 &
b111 %
#249
b111 !
b111 (
b11111001 #
b11111001 '
b11111001 &
b111 %
#250
b111 !
b111 (
b11111010 #
b11111010 '
b11111010 &
b111 %
#251
b111 !
b111 (
b11111011 #
b11111011 '
b11111011 &
b111 %
#252
b111 !
b111 (
b11111100 #
b11111100 '
b11111100 &
b111 %
#253
b111 !
b111 (
b11111101 #
b11111101 '
b11111101 &
b111 %
#254
b111 !
b111 (
b11111110 #
b11111110 '
b11111110 &
b111 %
#255
b111 !
b111 (
b11111111 #
b11111111 '
b11111111 &
b111 %
#256
b100000000 &
b111 %
