generated RTL/specified/bin2gray.syn.v
module bin2gray ( bin, gray );
  input [3:0] bin;
  output reg [3:0] gray;

  always @* begin
    gray[3] = bin[3];
    gray[2] = bin[3] ^ bin[2];
    gray[1] = bin[2] ^ bin[1];
    gray[0] = bin[1] ^ bin[0];
  end
endmodule

testbench/specified/tb_bin2gray.syn.v
module tb_bin2gray;
  reg  [3:0] bin;
  wire [3:0] gray;
  reg  [3:0] expected;

  bin2gray dut (.bin(bin), .gray(gray));

  always @* begin
    expected[3] = bin[3];
    expected[2] = bin[3] ^ bin[2];
    expected[1] = bin[2] ^ bin[1];
    expected[0] = bin[1] ^ bin[0];
  end

  integer i;
  initial begin
    $dumpfile("tb_bin2gray.vcd");
    $dumpvars(0, tb_bin2gray);
    for (i = 0; i < 16; i = i + 1) begin
      bin = i[3:0];
      #10;
    end
    #10 $finish;
  end

  initial begin
    $display(" time  bin  gray exp");
    $monitor("%4t   %b   %b   %b", $time, bin, gray, expected);
  end
endmodule

tb_bin2gray.vcd
$date
	Wed Apr 08 00:46:11 2026
$end
$version
	Icarus Verilog
$end
$timescale
	1s
$end
$scope module tb_bin2gray $end
$var wire 4 ! gray [3:0] $end
$var reg 4 " bin [3:0] $end
$var reg 4 # expected [3:0] $end
$var integer 32 $ i [31:0] $end
$scope module dut $end
$var wire 4 % bin [3:0] $end
$var reg 4 & gray [3:0] $end
$upscope $end
$upscope $end
$enddefinitions $end
#0
$dumpvars
b0 &
b0 %
b0 $
b0 #
b0 "
b0 !
$end
#10
b1 !
b1 &
b1 #
b1 "
b1 %
b1 $
#20
b11 #
b11 !
b11 &
b10 "
b10 %
b10 $
#30
b10 !
b10 &
b10 #
b11 "
b11 %
b11 $
#40
b110 #
b110 !
b110 &
b100 "
b100 %
b100 $
#50
b111 !
b111 &
b111 #
b101 "
b101 %
b101 $
#60
b101 #
b101 !
b101 &
b110 "
b110 %
b110 $
#70
b100 !
b100 &
b100 #
b111 "
b111 %
b111 $
#80
b1100 #
b1100 !
b1100 &
b1000 "
b1000 %
b1000 $
#90
b1101 !
b1101 &
b1101 #
b1001 "
b1001 %
b1001 $
#100
b1111 #
b1111 !
b1111 &
b1010 "
b1010 %
b1010 $
#110
b1110 !
b1110 &
b1110 #
b1011 "
b1011 %
b1011 $
#120
b1010 #
b1010 !
b1010 &
b1100 "
b1100 %
b1100 $
#130
b1011 !
b1011 &
b1011 #
b1101 "
b1101 %
b1101 $
#140
b1001 #
b1001 !
b1001 &
b1110 "
b1110 %
b1110 $
#150
b1000 !
b1000 &
b1000 #
b1111 "
b1111 %
b1111 $
#160
b10000 $
